shiki4py/__init__.py
shiki4py/api.py
shiki4py/base.py
shiki4py/exceptions.py
shiki4py/py.typed
shiki4py/resources/__init__.py
shiki4py/resources/animes.py
shiki4py/resources/base_resource.py
shiki4py/resources/comments.py
shiki4py/resources/users.py
shiki4py/store/__init__.py
shiki4py/store/env.py
shiki4py/store/memory.py
shiki4py/types/__init__.py
shiki4py/types/anime.py
shiki4py/types/anime_profile.py
shiki4py/types/ban.py
shiki4py/types/club.py
shiki4py/types/comment.py
shiki4py/types/external_link.py
shiki4py/types/favourite.py
shiki4py/types/favourites.py
shiki4py/types/franchise.py
shiki4py/types/linked_topic.py
shiki4py/types/manga.py
shiki4py/types/message.py
shiki4py/types/person_role.py
shiki4py/types/relation.py
shiki4py/types/screenshot.py
shiki4py/types/topic.py
shiki4py/types/unread_messages.py
shiki4py/types/user.py
shiki4py/types/user_history.py
shiki4py/types/user_info.py
shiki4py/types/user_profile.py
shiki4py/types/user_rate_full.py
shiki4py/types/video.py
shiki4py/utils.py
shiki4py-2.2.0.dist-info/LICENSE
shiki4py-2.2.0.dist-info/WHEEL
shiki4py-2.2.0.dist-info/METADATA
shiki4py-2.2.0.dist-info/RECORD
