Metadata-Version: 2.1
Name: shiki4py
Version: 2.2.0
Summary: Asynchronous client for api Shikimori written in Python 3.7 with asyncio and aiohttp.
Home-page: https://github.com/ren3104/Shiki4py
License: MIT
Keywords: api-client,aiohttp,asyncio,shikimori,anime
Author: ren3104
Author-email: 2ren3104@gmail.com
Requires-Python: >=3.7,<4.0
Classifier: License :: OSI Approved :: MIT License
Classifier: Programming Language :: Python :: 3
Classifier: Programming Language :: Python :: 3.10
Classifier: Programming Language :: Python :: 3.7
Classifier: Programming Language :: Python :: 3.8
Classifier: Programming Language :: Python :: 3.9
Requires-Dist: aiohttp (>=3.8.1,<4.0.0)
Requires-Dist: attrs (>=22.1.0,<23.0.0)
Requires-Dist: cattrs (>=22.1.0,<23.0.0)
Requires-Dist: pyrate-limiter (>=2.8.1,<3.0.0)
Requires-Dist: python-dotenv (>=0.20.0,<0.21.0)
Project-URL: Bug Tracker, https://github.com/ren3104/shikibaio/issues
Project-URL: Repository, https://github.com/ren3104/Shiki4py
